stratumrun/StratumRun.py
stratumrun/__init__.py
stratumrun-0.1.1.dist-info/LICENSE.txt
stratumrun-0.1.1.dist-info/METADATA
stratumrun-0.1.1.dist-info/WHEEL
stratumrun-0.1.1.dist-info/top_level.txt
stratumrun-0.1.1.dist-info/RECORD
