Metadata-Version: 2.1
Name: stratumrun
Version: 0.1.1
Summary: Stratum Run allows you to run scripts in various languages on the cloud
Home-page: https://bitbucket.org/pinetree-ai/lib-stratum-run-python3
Author: Aptus Engineering Inc.
Author-email: software@aptusai.com
License: UNKNOWN
Platform: UNKNOWN
Classifier: Programming Language :: Python :: 3
Classifier: License :: OSI Approved :: MIT License
Classifier: Operating System :: OS Independent
Requires-Python: >=3.6
Requires-Dist: requests
Requires-Dist: dataclasses
Requires-Dist: datetime
